{
"autoplayBgm":true,"autoplayBgs":false,"battleback1Name":"","battleback2Name":"","bgm":{"name":"","pan":0,"pitch":100,"volume":90},"bgs":{"name":"","pan":0,"pitch":100,"volume":90},"disableDashing":false,"displayName":"","encounterList":[],"encounterStep":30,"height":13,"note":"","parallaxLoopX":false,"parallaxLoopY":false,"parallaxName":"","parallaxShow":true,"parallaxSx":0,"parallaxSy":0,"scrollType":0,"specifyBattleback":false,"tilesetId":1,"width":17,
"data":[0,0,0,0,0,0,0,0,0,0,0,0,0,0,0,0,0,0,0,0,0,0,0,0,0,0,0,0,0,0,0,1537,1537,0,0,0,0,0,0,0,0,0,0,0,0,0,0,0,0,1537,0,0,0,0,0,0,0,0,0,0,0,0,0,0,0,1537,1537,0,0,1537,0,1537,0,0,0,0,0,0,0,0,0,0,0,0,0,0,1537,1537,1537,0,0,0,0,0,0,0,0,0,0,0,0,0,0,0,0,0,0,0,0,0,0,0,0,0,0,0,0,0,0,0,0,0,0,0,0,0,0,0,0,0,0,0,0,0,0,0,0,0,0,0,0,0,0,0,0,0,0,0,0,0,0,0,0,0,0,0,0,0,0,0,0,0,0,0,0,0,0,0,0,0,0,0,0,0,0,0,0,0,0,0,0,0,0,0,0,0,0,0,0,0,0,0,0,0,0,0,0,0,0,0,0,0,0,0,0,0,0,0,0,0,0,0,0,0,0,0,0,0,0,0,0,0,0,0,0,0,0,0,0,0,0,0,0,0,0,0,0,0,0,0,0,0,0,0,0,0,0,0,0,0,0,0,0,0,0,0,0,0,0,0,0,0,0,0,0,0,0,0,0,0,0,0,0,0,0,0,0,0,0,0,0,0,0,0,0,0,0,0,0,0,0,0,0,0,0,0,0,0,0,0,0,0,0,0,0,0,0,0,0,0,0,0,0,0,0,0,0,0,0,0,0,0,0,0,0,0,0,0,0,0,0,0,0,0,0,0,0,0,0,0,0,0,0,0,0,0,0,0,0,0,0,0,0,0,0,0,0,0,0,0,0,0,0,0,0,0,0,0,0,0,0,0,0,0,0,0,0,0,0,0,0,0,0,0,0,0,0,0,0,0,0,0,0,0,0,0,0,0,0,0,0,0,0,0,0,0,0,0,0,0,0,0,0,0,0,0,0,0,0,0,0,0,0,0,0,0,0,0,0,0,0,0,0,0,0,0,0,0,0,0,0,0,0,0,0,0,0,0,0,0,0,0,0,0,0,0,0,0,0,0,0,0,0,0,0,0,0,0,0,0,0,0,0,0,0,0,0,0,0,0,0,0,0,0,0,0,0,0,0,0,0,0,0,0,0,0,0,0,0,0,0,0,0,0,0,0,0,0,0,0,0,0,0,0,0,0,0,0,0,0,0,0,0,0,0,0,0,0,0,0,0,0,0,0,0,0,0,0,0,0,0,0,0,0,0,0,0,0,0,0,0,0,0,0,0,0,0,0,0,0,0,0,0,0,0,0,0,0,0,0,0,0,0,0,0,0,0,0,0,0,0,0,0,0,0,0,0,0,0,0,0,0,0,0,0,0,0,0,0,0,0,0,0,0,0,0,0,0,0,0,0,0,0,0,0,0,0,0,0,0,0,0,0,0,0,0,0,0,0,0,0,0,0,0,0,0,0,0,0,0,0,0,0,0,0,0,0,0,0,0,0,0,0,0,0,0,0,0,0,0,0,0,0,0,0,0,0,0,0,0,0,0,0,0,0,0,0,0,0,0,0,0,0,0,0,0,0,0,0,0,0,0,0,0,0,0,0,0,0,0,0,0,0,0,0,0,0,0,0,0,0,0,0,0,0,0,0,0,0,0,0,0,0,0,0,0,0,0,0,0,0,0,0,0,0,0,0,0,0,0,0,0,0,0,0,0,0,0,0,0,0,0,0,0,0,0,0,0,0,0,0,0,0,0,0,0,0,0,0,0,0,0,0,0,0,0,0,0,0,0,0,0,0,0,0,0,0,0,0,0,0,0,0,0,0,0,0,0,0,0,0,0,0,0,0,0,0,0,0,0,0,0,0,0,0,0,0,0,0,0,0,0,0,0,0,0,0,0,0,0,0,0,0,0,0,0,0,0,0,0,0,0,0,0,0,0,0,0,0,0,0,0,0,0,0,0,0,0,0,0,0,0,0,0,0,0,0,0,0,0,0,0,0,0,0,0,0,0,0,0,0,0,0,0,0,0,0,0,0,0,0,0,0,0,0,0,0,0,0,0,0,0,0,0,0,0,0,0,0,0,0,0,0,0,0,0,0,0,0,0,0,0,0,0,0,0,0,0,0,0,0,0,0,0,0,0,0,0,0,0,0,0,0,0,0,0,0,0,0,0,0,0,0,0,0,0,0,0,0,0,0,0,0,0,0,0,0,0,0,0,0,0,0,0,0,0,0,0,0,0,0,0,0,0,0,0,0,0,0,0,0,0,0,0,0,0,0,0,0,0,0,0,0,0,0,0,0,0,0,0,0,0,0,0,0,0,0,0,0,0,0,0,0,0,0,0,0,0,0,0,0,0,0,0,0,0,0,0,0,0,0,0,0,0,0,0,0,0,0,0,0,0,0,0,0,0,0,0,0,0,0,0,0,0,0,0,0,0,0,0,0,0,0,0,0,0,0,0,0,0,0,0,0,0,0,0,0,0,0,0,0,0,0,0,0,0,0,0,0,0,0,0,0,0,0,0,0,0,0,0,0,0,0,0,0,0,0,0,0,0,0,0,0,0,0,0,0,0,0,0,0,0,0,0,0,0,0,0,0,0,0,0,0,0,0,0,0,0,0,0,0,0,0,0,0,0,0,0,0,0,0,0,0,0,0,0,0,0,0,0,0,0,0,0,0,0,0,0,0,0,0,0,0,0,0,0,0,0,0,0,0,0,0,0,0,0,0,0,0,0,0,0,0,0,0,0,0,0,0,0,0,0,0,0,0,0,0,0,0,0,0,0,0,0,0,0,0,0,0,0,0,0,0,0,0,0,0,0,0,0,0,0,0,0,0,0,0,0,0,0,0,0,0,0,0,0,0,0,0,0,0,0,0,0,0,0,0,0,0,0,0,0,0,0,0,0,0,0,0,0,0,0,0,0,0,0,0,0,0,0,0,0,0,0,0,0,0,0,0,0,0,0,0,0,0,0,0,0,0,0,0,0,0,0,0,0,0,0,0,0,0,0,0,0,0,0],
"events":[
null,
{"id":1,"name":"EV001","note":"","pages":[{"conditions":{"actorId":1,"actorValid":false,"itemId":1,"itemValid":false,"selfSwitchCh":"A","selfSwitchValid":false,"switch1Id":1,"switch1Valid":false,"switch2Id":1,"switch2Valid":false,"variableId":1,"variableValid":false,"variableValue":0},"directionFix":false,"image":{"characterIndex":0,"characterName":"","direction":2,"pattern":0,"tileId":0},"list":[{"code":135,"indent":0,"parameters":[0]},{"code":355,"indent":0,"parameters":["//Graphics.requestFullScreen();"]},{"code":355,"indent":0,"parameters":["var result;"]},{"code":655,"indent":0,"parameters":["try {"]},{"code":655,"indent":0,"parameters":["var canvas = document.createElement('canvas');"]},{"code":655,"indent":0,"parameters":["var webGLContext = canvas.getContext(\"webgl\") || canvas.getContext(\"experimental-webgl\");"]},{"code":655,"indent":0,"parameters":["result = !!( window.WebGLRenderingContext && webGLContext && webGLContext.getShaderPrecisionFormat );"]},{"code":655,"indent":0,"parameters":["} catch (e) {"]},{"code":655,"indent":0,"parameters":["result = false;"]},{"code":655,"indent":0,"parameters":["}"]},{"code":655,"indent":0,"parameters":["$gameSwitches.setValue(5,result);"]},{"code":111,"indent":0,"parameters":[0,5,1]},{"code":112,"indent":1,"parameters":[]},{"code":101,"indent":2,"parameters":["",0,1,1]},{"code":401,"indent":2,"parameters":["Error! -- Failed to run WEBGL. --"]},{"code":401,"indent":2,"parameters":["あなたの環境ではこのデモは動きません。"]},{"code":401,"indent":2,"parameters":["端末かブラウザかグラフィックボードがWEBGLに非対応です。"]},{"code":401,"indent":2,"parameters":["WEBGLが動作する環境でお試しください。"]},{"code":0,"indent":2,"parameters":[]},{"code":413,"indent":1,"parameters":[]},{"code":0,"indent":1,"parameters":[]},{"code":412,"indent":0,"parameters":[]},{"code":230,"indent":0,"parameters":[60]},{"code":111,"indent":0,"parameters":[11,"shift"]},{"code":111,"indent":1,"parameters":[11,"pageup"]},{"code":201,"indent":2,"parameters":[0,13,16,0,0,0]},{"code":123,"indent":2,"parameters":["A",0]},{"code":0,"indent":2,"parameters":[]},{"code":412,"indent":1,"parameters":[]},{"code":0,"indent":1,"parameters":[]},{"code":412,"indent":0,"parameters":[]},{"code":111,"indent":0,"parameters":[12,"Utils.isMobileDevice()"]},{"code":101,"indent":1,"parameters":["",0,1,1]},{"code":401,"indent":1,"parameters":["Caution --Please run with sufficient line speed.--"]},{"code":401,"indent":1,"parameters":["快適な再生の為、十分なデータ通信速度で実行して下さい。"]},{"code":401,"indent":1,"parameters":["お使いのデバイスによっては、"]},{"code":401,"indent":1,"parameters":["完璧な動作を保障できませんのでご注意ください。\\|"]},{"code":102,"indent":1,"parameters":[["[同意する]"],-1,-1,1,1]},{"code":402,"indent":1,"parameters":[0,"[同意する]"]},{"code":0,"indent":2,"parameters":[]},{"code":404,"indent":1,"parameters":[]},{"code":0,"indent":1,"parameters":[]},{"code":412,"indent":0,"parameters":[]},{"code":111,"indent":0,"parameters":[12,"4>=(navigator.userAgent.indexOf('Android')>-1?navigator.userAgent.substr(navigator.userAgent.indexOf(\"Android \")+\"Android \".length,10).split(\".\")[0]:999999)"]},{"code":101,"indent":1,"parameters":["",0,1,1]},{"code":401,"indent":1,"parameters":["Caution --It may not work perfectly in your device.--"]},{"code":401,"indent":1,"parameters":["あなたのOSバージョンでは正常動作しないことがあります。"]},{"code":401,"indent":1,"parameters":["うまく動かない場合はバグレポートからではなく、"]},{"code":401,"indent":1,"parameters":["RPGアツマールの運営にお問い合わせください。\\|"]},{"code":102,"indent":1,"parameters":[["[同意する]"],-1,-1,1,1]},{"code":402,"indent":1,"parameters":[0,"[同意する]"]},{"code":0,"indent":2,"parameters":[]},{"code":404,"indent":1,"parameters":[]},{"code":0,"indent":1,"parameters":[]},{"code":412,"indent":0,"parameters":[]},{"code":111,"indent":0,"parameters":[12,"55>(navigator.userAgent.indexOf('Android')>-1?navigator.userAgent.substr(navigator.userAgent.indexOf(\"Chrome/\")+\"Chrome/\".length,20).split(\".\")[0]:999999)"]},{"code":101,"indent":1,"parameters":["",0,1,1]},{"code":401,"indent":1,"parameters":["Caution --It may not work perfectly in your browser.--"]},{"code":401,"indent":1,"parameters":["あなたのブラウザでは正常動作しないことがあります。"]},{"code":401,"indent":1,"parameters":["うまく動かない場合はバグレポートからではなく、"]},{"code":401,"indent":1,"parameters":["RPGアツマールの運営にお問い合わせください。\\|"]},{"code":102,"indent":1,"parameters":[["[同意する]"],-1,-1,1,1]},{"code":402,"indent":1,"parameters":[0,"[同意する]"]},{"code":0,"indent":2,"parameters":[]},{"code":404,"indent":1,"parameters":[]},{"code":0,"indent":1,"parameters":[]},{"code":412,"indent":0,"parameters":[]},{"code":111,"indent":0,"parameters":[2,"A",1]},{"code":241,"indent":1,"parameters":[{"name":"oriental_00_loop","volume":0,"pitch":100,"pan":0}]},{"code":231,"indent":1,"parameters":[1,"cube_a",0,0,0,0,100,100,0,0]},{"code":117,"indent":1,"parameters":[2]},{"code":231,"indent":1,"parameters":[1,"h2a_back",0,0,0,0,100,100,0,0]},{"code":117,"indent":1,"parameters":[2]},{"code":231,"indent":1,"parameters":[1,"icon",0,0,0,0,100,100,0,0]},{"code":117,"indent":1,"parameters":[2]},{"code":231,"indent":1,"parameters":[1,"showyou_a",0,0,0,0,100,100,0,0]},{"code":117,"indent":1,"parameters":[2]},{"code":231,"indent":1,"parameters":[1,"soul_a",0,0,0,0,100,100,0,0]},{"code":117,"indent":1,"parameters":[2]},{"code":231,"indent":1,"parameters":[1,"sushi_ani_00_a",0,0,0,0,100,100,0,0]},{"code":117,"indent":1,"parameters":[2]},{"code":231,"indent":1,"parameters":[1,"sushi_ani_01_a",0,0,0,0,100,100,0,0]},{"code":117,"indent":1,"parameters":[2]},{"code":231,"indent":1,"parameters":[1,"sushi_ani_02_a",0,0,0,0,100,100,0,0]},{"code":117,"indent":1,"parameters":[2]},{"code":231,"indent":1,"parameters":[1,"sushi_ani_03_a",0,0,0,0,100,100,0,0]},{"code":117,"indent":1,"parameters":[2]},{"code":231,"indent":1,"parameters":[1,"sushi_ani_04_a",0,0,0,0,100,100,0,0]},{"code":117,"indent":1,"parameters":[2]},{"code":231,"indent":1,"parameters":[1,"sushi_ani_05_a",0,0,0,0,100,100,0,0]},{"code":117,"indent":1,"parameters":[2]},{"code":231,"indent":1,"parameters":[1,"sushi_ani_06_a",0,0,0,0,100,100,0,0]},{"code":117,"indent":1,"parameters":[2]},{"code":231,"indent":1,"parameters":[1,"sushi_ani_07_a",0,0,0,0,100,100,0,0]},{"code":117,"indent":1,"parameters":[2]},{"code":231,"indent":1,"parameters":[1,"sushi_ani_08_a",0,0,0,0,100,100,0,0]},{"code":117,"indent":1,"parameters":[2]},{"code":231,"indent":1,"parameters":[1,"sushi_ani_09_a",0,0,0,0,100,100,0,0]},{"code":117,"indent":1,"parameters":[2]},{"code":231,"indent":1,"parameters":[1,"sushi_ani_10_a",0,0,0,0,100,100,0,0]},{"code":117,"indent":1,"parameters":[2]},{"code":231,"indent":1,"parameters":[1,"sushi_ani_11_a",0,0,0,0,100,100,0,0]},{"code":117,"indent":1,"parameters":[2]},{"code":231,"indent":1,"parameters":[1,"wakka",0,0,0,0,100,100,0,0]},{"code":117,"indent":1,"parameters":[2]},{"code":231,"indent":1,"parameters":[1,"pack",0,0,0,0,100,100,0,0]},{"code":117,"indent":1,"parameters":[2]},{"code":231,"indent":1,"parameters":[1,"pizza_a",0,0,0,0,100,100,0,0]},{"code":117,"indent":1,"parameters":[2]},{"code":117,"indent":1,"parameters":[3]},{"code":235,"indent":1,"parameters":[1]},{"code":241,"indent":1,"parameters":[{"name":"","volume":0,"pitch":100,"pan":0}]},{"code":230,"indent":1,"parameters":[60]},{"code":201,"indent":1,"parameters":[0,7,14,0,0,0]},{"code":0,"indent":1,"parameters":[]},{"code":411,"indent":0,"parameters":[]},{"code":214,"indent":1,"parameters":[]},{"code":0,"indent":1,"parameters":[]},{"code":412,"indent":0,"parameters":[]},{"code":0,"indent":0,"parameters":[]}],"moveFrequency":3,"moveRoute":{"list":[{"code":0,"parameters":[]}],"repeat":true,"skippable":false,"wait":false},"moveSpeed":3,"moveType":0,"priorityType":0,"stepAnime":false,"through":false,"trigger":3,"walkAnime":true}],"x":0,"y":0},
{"id":2,"name":"EV002","note":"","pages":[{"conditions":{"actorId":1,"actorValid":false,"itemId":1,"itemValid":false,"selfSwitchCh":"A","selfSwitchValid":false,"switch1Id":1,"switch1Valid":false,"switch2Id":1,"switch2Valid":false,"variableId":1,"variableValid":false,"variableValue":0},"directionFix":false,"image":{"tileId":0,"characterName":"alpha","direction":8,"pattern":2,"characterIndex":0},"list":[{"code":0,"indent":0,"parameters":[]}],"moveFrequency":3,"moveRoute":{"list":[{"code":0,"parameters":[]}],"repeat":true,"skippable":false,"wait":false},"moveSpeed":3,"moveType":0,"priorityType":1,"stepAnime":false,"through":false,"trigger":0,"walkAnime":true}],"x":2,"y":8},
{"id":3,"name":"EV003","note":"","pages":[{"conditions":{"actorId":1,"actorValid":false,"itemId":1,"itemValid":false,"selfSwitchCh":"A","selfSwitchValid":false,"switch1Id":1,"switch1Valid":false,"switch2Id":1,"switch2Valid":false,"variableId":7,"variableValid":true,"variableValue":10},"directionFix":false,"image":{"tileId":1,"characterName":"","characterIndex":0,"direction":2,"pattern":0},"list":[{"code":0,"indent":0,"parameters":[]}],"moveFrequency":5,"moveRoute":{"list":[{"code":14,"parameters":[0,0],"indent":null},{"code":0,"parameters":[]}],"repeat":true,"skippable":false,"wait":false},"moveSpeed":6,"moveType":3,"priorityType":0,"stepAnime":false,"through":false,"trigger":0,"walkAnime":true}],"x":2,"y":4},
{"id":4,"name":"EV004","note":"","pages":[{"conditions":{"actorId":1,"actorValid":false,"itemId":1,"itemValid":false,"selfSwitchCh":"A","selfSwitchValid":false,"switch1Id":1,"switch1Valid":false,"switch2Id":1,"switch2Valid":false,"variableId":7,"variableValid":true,"variableValue":20},"directionFix":false,"image":{"tileId":1,"characterName":"","characterIndex":0,"direction":2,"pattern":0},"list":[{"code":0,"indent":0,"parameters":[]}],"moveFrequency":5,"moveRoute":{"list":[{"code":14,"parameters":[0,0],"indent":null},{"code":0,"parameters":[]}],"repeat":true,"skippable":false,"wait":false},"moveSpeed":3,"moveType":3,"priorityType":0,"stepAnime":false,"through":false,"trigger":0,"walkAnime":true}],"x":2,"y":2},
{"id":5,"name":"EV005","note":"","pages":[{"conditions":{"actorId":1,"actorValid":false,"itemId":1,"itemValid":false,"selfSwitchCh":"A","selfSwitchValid":false,"switch1Id":1,"switch1Valid":false,"switch2Id":1,"switch2Valid":false,"variableId":7,"variableValid":true,"variableValue":30},"directionFix":false,"image":{"tileId":1,"characterName":"","characterIndex":0,"direction":2,"pattern":0},"list":[{"code":0,"indent":0,"parameters":[]}],"moveFrequency":5,"moveRoute":{"list":[{"code":14,"parameters":[0,0],"indent":null},{"code":0,"parameters":[]}],"repeat":true,"skippable":false,"wait":false},"moveSpeed":3,"moveType":3,"priorityType":0,"stepAnime":false,"through":false,"trigger":0,"walkAnime":true}],"x":4,"y":2},
{"id":6,"name":"EV006","note":"","pages":[{"conditions":{"actorId":1,"actorValid":false,"itemId":1,"itemValid":false,"selfSwitchCh":"A","selfSwitchValid":false,"switch1Id":1,"switch1Valid":false,"switch2Id":1,"switch2Valid":false,"variableId":7,"variableValid":true,"variableValue":40},"directionFix":false,"image":{"tileId":1,"characterName":"","characterIndex":0,"direction":2,"pattern":0},"list":[{"code":0,"indent":0,"parameters":[]}],"moveFrequency":5,"moveRoute":{"list":[{"code":14,"parameters":[0,0],"indent":null},{"code":0,"parameters":[]}],"repeat":true,"skippable":false,"wait":false},"moveSpeed":3,"moveType":3,"priorityType":0,"stepAnime":false,"through":false,"trigger":0,"walkAnime":true}],"x":6,"y":2},
{"id":7,"name":"EV007","note":"","pages":[{"conditions":{"actorId":1,"actorValid":false,"itemId":1,"itemValid":false,"selfSwitchCh":"A","selfSwitchValid":false,"switch1Id":1,"switch1Valid":false,"switch2Id":1,"switch2Valid":false,"variableId":7,"variableValid":true,"variableValue":50},"directionFix":false,"image":{"tileId":1,"characterName":"","characterIndex":0,"direction":2,"pattern":0},"list":[{"code":0,"indent":0,"parameters":[]}],"moveFrequency":5,"moveRoute":{"list":[{"code":14,"parameters":[0,0],"indent":null},{"code":0,"parameters":[]}],"repeat":true,"skippable":false,"wait":false},"moveSpeed":3,"moveType":3,"priorityType":0,"stepAnime":false,"through":false,"trigger":0,"walkAnime":true}],"x":8,"y":2},
{"id":8,"name":"EV008","note":"","pages":[{"conditions":{"actorId":1,"actorValid":false,"itemId":1,"itemValid":false,"selfSwitchCh":"A","selfSwitchValid":false,"switch1Id":1,"switch1Valid":false,"switch2Id":1,"switch2Valid":false,"variableId":7,"variableValid":true,"variableValue":60},"directionFix":false,"image":{"tileId":1,"characterName":"","characterIndex":0,"direction":2,"pattern":0},"list":[{"code":0,"indent":0,"parameters":[]}],"moveFrequency":5,"moveRoute":{"list":[{"code":14,"parameters":[0,0],"indent":null},{"code":0,"parameters":[]}],"repeat":true,"skippable":false,"wait":false},"moveSpeed":3,"moveType":3,"priorityType":0,"stepAnime":false,"through":false,"trigger":0,"walkAnime":true}],"x":8,"y":4},
{"id":9,"name":"EV009","note":"","pages":[{"conditions":{"actorId":1,"actorValid":false,"itemId":1,"itemValid":false,"selfSwitchCh":"A","selfSwitchValid":false,"switch1Id":1,"switch1Valid":false,"switch2Id":1,"switch2Valid":false,"variableId":7,"variableValid":true,"variableValue":70},"directionFix":false,"image":{"tileId":1,"characterName":"","characterIndex":0,"direction":2,"pattern":0},"list":[{"code":0,"indent":0,"parameters":[]}],"moveFrequency":5,"moveRoute":{"list":[{"code":14,"parameters":[0,0],"indent":null},{"code":0,"parameters":[]}],"repeat":true,"skippable":false,"wait":false},"moveSpeed":3,"moveType":3,"priorityType":0,"stepAnime":false,"through":false,"trigger":0,"walkAnime":true}],"x":10,"y":4},
{"id":10,"name":"EV010","note":"","pages":[{"conditions":{"actorId":1,"actorValid":false,"itemId":1,"itemValid":false,"selfSwitchCh":"A","selfSwitchValid":false,"switch1Id":1,"switch1Valid":false,"switch2Id":1,"switch2Valid":false,"variableId":7,"variableValid":true,"variableValue":80},"directionFix":false,"image":{"tileId":1,"characterName":"","characterIndex":0,"direction":2,"pattern":0},"list":[{"code":0,"indent":0,"parameters":[]}],"moveFrequency":5,"moveRoute":{"list":[{"code":14,"parameters":[0,0],"indent":null},{"code":37,"indent":null},{"code":5,"indent":null},{"code":5,"indent":null},{"code":27,"parameters":[11],"indent":null},{"code":5,"indent":null},{"code":5,"indent":null},{"code":5,"indent":null},{"code":5,"indent":null},{"code":5,"indent":null},{"code":5,"indent":null},{"code":5,"indent":null},{"code":5,"indent":null},{"code":5,"indent":null},{"code":5,"indent":null},{"code":5,"indent":null},{"code":5,"indent":null},{"code":5,"indent":null},{"code":5,"indent":null},{"code":5,"indent":null},{"code":5,"indent":null},{"code":0,"parameters":[]}],"repeat":false,"skippable":true,"wait":false},"moveSpeed":4,"moveType":3,"priorityType":0,"stepAnime":false,"through":false,"trigger":0,"walkAnime":true}],"x":12,"y":4},
{"id":11,"name":"EV011","note":"","pages":[{"conditions":{"actorId":1,"actorValid":false,"itemId":1,"itemValid":false,"selfSwitchCh":"A","selfSwitchValid":false,"switch1Id":1,"switch1Valid":false,"switch2Id":1,"switch2Valid":false,"variableId":7,"variableValid":true,"variableValue":90},"directionFix":false,"image":{"tileId":1,"characterName":"","characterIndex":0,"direction":2,"pattern":0},"list":[{"code":0,"indent":0,"parameters":[]}],"moveFrequency":5,"moveRoute":{"list":[{"code":14,"parameters":[0,0],"indent":null},{"code":0,"parameters":[]}],"repeat":true,"skippable":false,"wait":false},"moveSpeed":3,"moveType":3,"priorityType":0,"stepAnime":false,"through":false,"trigger":0,"walkAnime":true}],"x":12,"y":2},
{"id":12,"name":"EV012","note":"","pages":[{"conditions":{"actorId":1,"actorValid":false,"itemId":1,"itemValid":false,"selfSwitchCh":"A","selfSwitchValid":false,"switch1Id":1,"switch1Valid":false,"switch2Id":1,"switch2Valid":false,"variableId":7,"variableValid":true,"variableValue":100},"directionFix":false,"image":{"tileId":1,"characterName":"","characterIndex":0,"direction":2,"pattern":0},"list":[{"code":0,"indent":0,"parameters":[]}],"moveFrequency":5,"moveRoute":{"list":[{"code":14,"parameters":[0,0],"indent":null},{"code":0,"parameters":[]}],"repeat":true,"skippable":false,"wait":false},"moveSpeed":6,"moveType":3,"priorityType":0,"stepAnime":false,"through":false,"trigger":0,"walkAnime":true}],"x":14,"y":2},
{"id":13,"name":"EV013","note":"","pages":[{"conditions":{"actorId":1,"actorValid":false,"itemId":1,"itemValid":false,"selfSwitchCh":"A","selfSwitchValid":false,"switch1Id":1,"switch1Valid":false,"switch2Id":1,"switch2Valid":false,"variableId":1,"variableValid":false,"variableValue":0},"directionFix":false,"image":{"tileId":0,"characterName":"alpha","direction":2,"pattern":2,"characterIndex":1},"list":[{"code":0,"indent":0,"parameters":[]}],"moveFrequency":3,"moveRoute":{"list":[{"code":0,"parameters":[]}],"repeat":true,"skippable":false,"wait":false},"moveSpeed":3,"moveType":0,"priorityType":1,"stepAnime":false,"through":false,"trigger":0,"walkAnime":true}],"x":4,"y":8},
{"id":14,"name":"EV014","note":"","pages":[{"conditions":{"actorId":1,"actorValid":false,"itemId":1,"itemValid":false,"selfSwitchCh":"A","selfSwitchValid":false,"switch1Id":1,"switch1Valid":false,"switch2Id":1,"switch2Valid":false,"variableId":1,"variableValid":false,"variableValue":0},"directionFix":false,"image":{"tileId":0,"characterName":"alpha","direction":2,"pattern":0,"characterIndex":0},"list":[{"code":0,"indent":0,"parameters":[]}],"moveFrequency":3,"moveRoute":{"list":[{"code":0,"parameters":[]}],"repeat":true,"skippable":false,"wait":false},"moveSpeed":3,"moveType":0,"priorityType":1,"stepAnime":false,"through":false,"trigger":0,"walkAnime":true}],"x":6,"y":8},
{"id":15,"name":"EV015","note":"","pages":[{"conditions":{"actorId":1,"actorValid":false,"itemId":1,"itemValid":false,"selfSwitchCh":"A","selfSwitchValid":false,"switch1Id":1,"switch1Valid":false,"switch2Id":1,"switch2Valid":false,"variableId":1,"variableValid":false,"variableValue":0},"directionFix":false,"image":{"tileId":0,"characterName":"alpha","direction":4,"pattern":0,"characterIndex":0},"list":[{"code":0,"indent":0,"parameters":[]}],"moveFrequency":3,"moveRoute":{"list":[{"code":0,"parameters":[]}],"repeat":true,"skippable":false,"wait":false},"moveSpeed":3,"moveType":0,"priorityType":1,"stepAnime":false,"through":false,"trigger":0,"walkAnime":true},{"conditions":{"actorId":1,"actorValid":false,"itemId":1,"itemValid":false,"selfSwitchCh":"A","selfSwitchValid":false,"switch1Id":11,"switch1Valid":true,"switch2Id":1,"switch2Valid":false,"variableId":1,"variableValid":false,"variableValue":0},"directionFix":true,"image":{"tileId":0,"characterName":"alpha","direction":4,"pattern":0,"characterIndex":0},"list":[{"code":0,"indent":0,"parameters":[]}],"moveFrequency":5,"moveRoute":{"list":[{"code":2,"indent":null},{"code":0,"parameters":[]}],"repeat":false,"skippable":false,"wait":false},"moveSpeed":4,"moveType":3,"priorityType":1,"stepAnime":false,"through":true,"trigger":0,"walkAnime":false}],"x":8,"y":8},
{"id":16,"name":"EV016","note":"","pages":[{"conditions":{"actorId":1,"actorValid":false,"itemId":1,"itemValid":false,"selfSwitchCh":"A","selfSwitchValid":false,"switch1Id":1,"switch1Valid":false,"switch2Id":1,"switch2Valid":false,"variableId":1,"variableValid":false,"variableValue":0},"directionFix":false,"image":{"tileId":0,"characterName":"alpha","direction":6,"pattern":2,"characterIndex":0},"list":[{"code":0,"indent":0,"parameters":[]}],"moveFrequency":3,"moveRoute":{"list":[{"code":0,"parameters":[]}],"repeat":true,"skippable":false,"wait":false},"moveSpeed":3,"moveType":3,"priorityType":1,"stepAnime":false,"through":false,"trigger":0,"walkAnime":true},{"conditions":{"actorId":1,"actorValid":false,"itemId":1,"itemValid":false,"selfSwitchCh":"A","selfSwitchValid":false,"switch1Id":11,"switch1Valid":true,"switch2Id":1,"switch2Valid":false,"variableId":1,"variableValid":false,"variableValue":0},"directionFix":false,"image":{"tileId":0,"characterName":"alpha","direction":6,"pattern":2,"characterIndex":0},"list":[{"code":0,"indent":0,"parameters":[]}],"moveFrequency":5,"moveRoute":{"list":[{"code":15,"parameters":[10],"indent":null},{"code":3,"indent":null},{"code":33,"indent":null},{"code":0,"parameters":[]}],"repeat":false,"skippable":false,"wait":false},"moveSpeed":6,"moveType":3,"priorityType":1,"stepAnime":false,"through":true,"trigger":0,"walkAnime":true}],"x":10,"y":8},
{"id":17,"name":"EV017","note":"","pages":[{"conditions":{"actorId":1,"actorValid":false,"itemId":1,"itemValid":false,"selfSwitchCh":"A","selfSwitchValid":false,"switch1Id":1,"switch1Valid":false,"switch2Id":1,"switch2Valid":false,"variableId":1,"variableValid":false,"variableValue":0},"directionFix":false,"image":{"tileId":0,"characterName":"alpha","direction":2,"pattern":1,"characterIndex":1},"list":[{"code":0,"indent":0,"parameters":[]}],"moveFrequency":3,"moveRoute":{"list":[{"code":0,"parameters":[]}],"repeat":true,"skippable":false,"wait":false},"moveSpeed":3,"moveType":0,"priorityType":1,"stepAnime":false,"through":false,"trigger":0,"walkAnime":true}],"x":12,"y":8},
{"id":18,"name":"EV018","note":"","pages":[{"conditions":{"actorId":1,"actorValid":false,"itemId":1,"itemValid":false,"selfSwitchCh":"A","selfSwitchValid":false,"switch1Id":1,"switch1Valid":false,"switch2Id":1,"switch2Valid":false,"variableId":1,"variableValid":false,"variableValue":0},"directionFix":false,"image":{"tileId":0,"characterName":"alpha","direction":6,"pattern":0,"characterIndex":0},"list":[{"code":0,"indent":0,"parameters":[]}],"moveFrequency":3,"moveRoute":{"list":[{"code":0,"parameters":[]}],"repeat":true,"skippable":false,"wait":false},"moveSpeed":3,"moveType":0,"priorityType":1,"stepAnime":false,"through":false,"trigger":0,"walkAnime":true}],"x":14,"y":8},
null
]
}